<?xml version="1.0" encoding="UTF-8"?>
<objects serializationModel="Studio.02.02.00">
	<object class="AudioFile" id="{757b6c72-9451-420b-a33a-09baedb50f14}">
		<property name="assetPath">
			<value>LAST SFX/Sonar Reveals Wall.aif</value>
		</property>
		<property name="frequencyInKHz">
			<value>44.0999985</value>
		</property>
		<property name="channelCount">
			<value>2</value>
		</property>
		<property name="length">
			<value>2.7859863945578232</value>
		</property>
		<relationship name="masterAssetFolder">
			<destination>{5553b94c-a3ad-48e6-b402-5e6f22f449e8}</destination>
		</relationship>
	</object>
</objects>
